fmd/__init__.py
fmd/backend.py
fmd/base.py
fmd/client.py
fmd/decorators.py
fmd/exceptions.py
fmd/resources/__init__.py
fmd/resources/etf/__init__.py
fmd/resources/etf/obj.py
fmd/resources/etf/types.py
fmd/resources/forex/__init__.py
fmd/resources/forex/obj.py
fmd/resources/forex/types.py
fmd/resources/index/__init__.py
fmd/resources/index/obj.py
fmd/resources/index/types.py
fmd/resources/stock/__init__.py
fmd/resources/stock/obj.py
fmd/resources/stock/types.py
fmd-0.6.1.dist-info/LICENSE
fmd-0.6.1.dist-info/METADATA
fmd-0.6.1.dist-info/WHEEL
fmd-0.6.1.dist-info/RECORD
