Metadata-Version: 2.3
Name: fmd
Version: 0.6.1
Summary: Download Taiwan financial market data via FMD API.
License: Apache-2.0
Author: Yu Chen, Yang
Author-email: ycy.tai@gmail.com
Requires-Python: >=3.10,<4.0
Classifier: License :: OSI Approved :: Apache Software License
Classifier: Programming Language :: Python :: 3
Classifier: Programming Language :: Python :: 3.10
Classifier: Programming Language :: Python :: 3.11
Classifier: Programming Language :: Python :: 3.12
Classifier: Programming Language :: Python :: 3.13
Requires-Dist: requests (>=2.32.3,<3.0.0)
Requires-Dist: typing-extensions (>=4.12.2,<5.0.0)
Project-URL: Homepage, https://github.com/ycytai/fmd
